<instance version="4" override_type="merge" description="English Villager" template="sbps">
	<list name="extensions" overrideParent="True">
		<template_reference name="squadexts" value="sbpextensions\squad_engineer_ext" overrideParent="True" List.ItemID="2108547692" List.ParentItemID="851310113">
			<float name="construction_rate_multiplier" value="1" />
			<list name="construction_groups" overrideParent="True">
				<group name="construction_group" comment="Dark Age" overrideParent="True" List.ItemID="718034620">
					<instance_reference name="construction_menu" value="menu\rus_age1" />
					<list name="construction_items" overrideParent="True">
						<group name="construction_item" comment="Wooden Fortress" List.ItemID="251587881">
							<instance_reference name="ebp" value="ebps\races\rus\buildings\building_defense_wooden_fort_rus\building_defense_wooden_fort_rus" />
							<group name="ui_position">
								<int name="ui_position_row" value="3" />
								<int name="ui_position_column" value="1" overrideParent="True" />
							</group>
							<list name="associated_ebps">
							</list>
							<instance_reference name="hotkey_binding" value="hotkeys\hotkey_binding\villager_build_menu\age_1\build_wooden_fortress" overrideParent="True" />
							<list name="alternate_ebps">
							</list>
							<list name="additional_requirements">
							</list>
							<state_tree_node name="additional_requirement_statetree" value="" />
						</group>
						<group name="construction_item" comment="Barracks" List.ItemID="291270599">
							<instance_reference name="ebp" value="ebps\races\rus\buildings\building_unit_infantry_rus\building_unit_infantry_control_rus" />
							<group name="ui_position">
								<int name="ui_position_row" value="2" />
								<int name="ui_position_column" value="2" overrideParent="True" />
							</group>
							<list name="associated_ebps">
							</list>
							<instance_reference name="hotkey_binding" value="hotkeys\hotkey_binding\villager_build_menu\age_1\build_barracks" overrideParent="True" />
							<list name="alternate_ebps">
							</list>
							<list name="additional_requirements">
							</list>
							<state_tree_node name="additional_requirement_statetree" value="" />
						</group>
						<group name="construction_item" comment="Palisade" List.ItemID="1157754362">
							<instance_reference name="ebp" value="ebps\races\rus\buildings\building_defense_wall_rus\building_defense_palisade_rus" />
							<group name="ui_position">
								<int name="ui_position_row" value="3" />
								<int name="ui_position_column" value="2" overrideParent="True" />
							</group>
							<list name="associated_ebps">
							</list>
							<instance_reference name="hotkey_binding" value="hotkeys\hotkey_binding\villager_build_menu\age_1\build_palisade" overrideParent="True" />
							<list name="alternate_ebps">
							</list>
							<list name="additional_requirements">
							</list>
							<state_tree_node name="additional_requirement_statetree" value="" />
						</group>
						<group name="construction_item" comment="Dock" List.ItemID="601055656">
							<instance_reference name="ebp" value="ebps\races\rus\buildings\building_unit_naval_rus\building_unit_naval_rus" overrideParent="True" />
							<group name="ui_position">
								<int name="ui_position_row" value="2" overrideParent="True" />
								<int name="ui_position_column" value="3" overrideParent="True" />
							</group>
							<list name="associated_ebps">
							</list>
							<instance_reference name="hotkey_binding" value="hotkeys\hotkey_binding\villager_build_menu\age_1\build_dock" overrideParent="True" />
							<list name="alternate_ebps">
							</list>
							<list name="additional_requirements">
							</list>
							<state_tree_node name="additional_requirement_statetree" value="" />
						</group>
						<group name="construction_item" comment="Palisade Gate" List.ItemID="-883343025">
							<instance_reference name="ebp" value="ebps\races\rus\buildings\building_defense_wall_rus\building_defense_palisade_gate_rus" />
							<group name="ui_position">
								<int name="ui_position_row" value="3" />
								<int name="ui_position_column" value="3" overrideParent="True" />
							</group>
							<list name="associated_ebps">
							</list>
							<instance_reference name="hotkey_binding" value="hotkeys\hotkey_binding\villager_build_menu\age_1\build_palisade_gate" overrideParent="True" />
							<list name="alternate_ebps">
							</list>
							<list name="additional_requirements">
							</list>
							<state_tree_node name="additional_requirement_statetree" value="" />
						</group>
						<group name="construction_item" comment="Palisade Bastion" List.ItemID="283878191">
							<instance_reference name="ebp" value="ebps\races\rus\buildings\building_defense_wall_rus\building_defense_palisade_bastion_rus" overrideParent="True" />
							<group name="ui_position">
								<int name="ui_position_row" value="-1" />
								<int name="ui_position_column" value="-1" />
							</group>
							<list name="associated_ebps">
							</list>
							<instance_reference name="hotkey_binding" value="" />
							<list name="alternate_ebps">
							</list>
							<list name="additional_requirements">
							</list>
							<state_tree_node name="additional_requirement_statetree" value="" />
						</group>
					</list>
					<enum name="construction_type" value="tp_construction_base" />
				</group>
				<group name="construction_group" comment="Feudal Age" List.ItemID="750142594">
					<instance_reference name="construction_menu" value="menu\rus_age2" />
					<list name="construction_items" overrideParent="True">
						<group name="construction_item" comment="Blacksmith" List.ItemID="-717568744">
							<instance_reference name="ebp" value="ebps\races\rus\buildings\building_tech_unit_infantry_rus\building_tech_unit_infantry_control_rus" />
							<group name="ui_position">
								<int name="ui_position_row" value="1" />
								<int name="ui_position_column" value="1" overrideParent="True" />
							</group>
							<list name="associated_ebps">
							</list>
							<instance_reference name="hotkey_binding" value="hotkeys\hotkey_binding\villager_build_menu\age_2\build_blacksmith" overrideParent="True" />
							<list name="alternate_ebps">
							</list>
							<list name="additional_requirements">
							</list>
							<state_tree_node name="additional_requirement_statetree" value="" />
						</group>
						<group name="construction_item" comment="Archery Range" List.ItemID="-2100092618">
							<instance_reference name="ebp" value="ebps\races\rus\buildings\building_unit_ranged_rus\building_unit_ranged_control_rus" />
							<group name="ui_position">
								<int name="ui_position_row" value="2" />
								<int name="ui_position_column" value="1" />
							</group>
							<list name="associated_ebps">
							</list>
							<instance_reference name="hotkey_binding" value="hotkeys\hotkey_binding\villager_build_menu\age_2\build_archery_range" overrideParent="True" />
							<list name="alternate_ebps">
							</list>
							<list name="additional_requirements">
							</list>
							<state_tree_node name="additional_requirement_statetree" value="" />
						</group>
						<group name="construction_item" comment="Stable" List.ItemID="-1730760901">
							<instance_reference name="ebp" value="ebps\races\rus\buildings\building_unit_cavalry_rus\building_unit_cavalry_control_rus" />
							<group name="ui_position">
								<int name="ui_position_row" value="2" />
								<int name="ui_position_column" value="2" />
							</group>
							<list name="associated_ebps">
							</list>
							<instance_reference name="hotkey_binding" value="hotkeys\hotkey_binding\villager_build_menu\age_2\build_stable" overrideParent="True" />
							<list name="alternate_ebps">
							</list>
							<list name="additional_requirements">
							</list>
							<state_tree_node name="additional_requirement_statetree" value="" />
						</group>
						<group name="construction_item" comment="Wall" List.ItemID="-1499032946">
							<instance_reference name="ebp" value="ebps\races\rus\buildings\building_defense_wall_rus\building_defense_wall_rus" overrideParent="True" />
							<group name="ui_position">
								<int name="ui_position_row" value="3" />
								<int name="ui_position_column" value="2" overrideParent="True" />
							</group>
							<list name="associated_ebps">
							</list>
							<list name="alternate_ebps">
							</list>
							<instance_reference name="hotkey_binding" value="" />
							<list name="additional_requirements">
							</list>
							<state_tree_node name="additional_requirement_statetree" value="" />
						</group>
						<group name="construction_item" comment="Wall Bastion" List.ItemID="-1405848055">
							<instance_reference name="ebp" value="ebps\races\rus\buildings\building_defense_wall_rus\building_defense_wall_bastion_rus" overrideParent="True" />
							<group name="ui_position">
								<int name="ui_position_row" value="-1" />
								<int name="ui_position_column" value="-1" />
							</group>
							<list name="associated_ebps">
							</list>
							<list name="alternate_ebps">
							</list>
							<instance_reference name="hotkey_binding" value="" />
							<list name="additional_requirements">
							</list>
							<state_tree_node name="additional_requirement_statetree" value="" />
						</group>
						<group name="construction_item" comment="Wall Gate" List.ItemID="-1410058703">
							<instance_reference name="ebp" value="ebps\races\rus\buildings\building_defense_wall_rus\building_defense_wall_gate_rus" overrideParent="True" />
							<group name="ui_position">
								<int name="ui_position_row" value="3" />
								<int name="ui_position_column" value="3" overrideParent="True" />
							</group>
							<list name="associated_ebps">
							</list>
							<list name="alternate_ebps">
							</list>
							<instance_reference name="hotkey_binding" value="" />
							<list name="additional_requirements">
							</list>
							<state_tree_node name="additional_requirement_statetree" value="" />
						</group>
						<group name="construction_item" comment="Tower" List.ItemID="-2045890198">
							<instance_reference name="ebp" value="ebps\races\rus\buildings\building_defense_wall_rus\building_defense_tower_rus" overrideParent="True" />
							<group name="ui_position">
								<int name="ui_position_row" value="3" />
								<int name="ui_position_column" value="1" overrideParent="True" />
							</group>
							<list name="associated_ebps">
							</list>
							<list name="alternate_ebps">
							</list>
							<instance_reference name="hotkey_binding" value="" />
							<list name="additional_requirements">
							</list>
							<state_tree_node name="additional_requirement_statetree" value="" />
						</group>
					</list>
					<enum name="construction_type" value="tp_construction_base" />
				</group>
				<group name="construction_group" comment="Castle Age" List.ItemID="1382686773">
					<instance_reference name="construction_menu" value="menu\rus_age3" />
					<list name="construction_items" overrideParent="True">
						<group name="construction_item" comment="Siege Workshop&#xD;&#xA;" List.ItemID="-805811378">
							<instance_reference name="ebp" value="ebps\races\rus\buildings\building_unit_siege_rus\building_unit_siege_control_rus" />
							<group name="ui_position">
								<int name="ui_position_row" value="2" overrideParent="True" />
								<int name="ui_position_column" value="1" overrideParent="True" />
							</group>
							<list name="associated_ebps">
							</list>
							<instance_reference name="hotkey_binding" value="hotkeys\hotkey_binding\villager_build_menu\age_3\build_siege_workshop" overrideParent="True" />
							<list name="alternate_ebps">
							</list>
							<list name="additional_requirements">
							</list>
							<state_tree_node name="additional_requirement_statetree" value="" />
						</group>
						<group name="construction_item" comment="Keep" List.ItemID="859269855">
							<instance_reference name="ebp" value="ebps\races\rus\buildings\building_defense_keep_rus\building_defense_keep_control_rus" />
							<group name="ui_position">
								<int name="ui_position_row" value="3" overrideParent="True" />
								<int name="ui_position_column" value="1" overrideParent="True" />
							</group>
							<list name="associated_ebps">
							</list>
							<instance_reference name="hotkey_binding" value="hotkeys\hotkey_binding\villager_build_menu\age_3\build_keep" overrideParent="True" />
							<list name="alternate_ebps">
							</list>
							<list name="additional_requirements">
							</list>
							<state_tree_node name="additional_requirement_statetree" value="" />
						</group>
						<group name="construction_item" comment="Monastery" List.ItemID="366913714">
							<instance_reference name="ebp" value="ebps\races\rus\buildings\building_unit_religious_rus\building_unit_religious_control_rus" />
							<group name="ui_position">
								<int name="ui_position_row" value="1" overrideParent="True" />
								<int name="ui_position_column" value="1" overrideParent="True" />
							</group>
							<list name="associated_ebps">
							</list>
							<instance_reference name="hotkey_binding" value="hotkeys\hotkey_binding\villager_build_menu\age_3\build_monastery" overrideParent="True" />
							<list name="alternate_ebps">
							</list>
							<list name="additional_requirements">
							</list>
							<state_tree_node name="additional_requirement_statetree" value="" />
						</group>
					</list>
					<enum name="construction_type" value="tp_construction_base" />
				</group>
				<group name="construction_group" comment="Imperial Age" List.ItemID="-2137290808">
					<instance_reference name="construction_menu" value="menu\rus_age4" />
					<list name="construction_items" overrideParent="True">
						<group name="construction_item" comment="University" List.ItemID="144307665">
							<instance_reference name="ebp" value="ebps\races\rus\buildings\building_tech_university_rus\building_tech_university_control_rus" />
							<group name="ui_position">
								<int name="ui_position_row" value="1" overrideParent="True" />
								<int name="ui_position_column" value="1" />
							</group>
							<list name="associated_ebps">
							</list>
							<instance_reference name="hotkey_binding" value="hotkeys\hotkey_binding\villager_build_menu\age_4\build_university" overrideParent="True" />
							<list name="alternate_ebps">
							</list>
							<list name="additional_requirements">
							</list>
							<state_tree_node name="additional_requirement_statetree" value="" />
						</group>
					</list>
					<enum name="construction_type" value="tp_construction_base" />
				</group>
			</list>
		</template_reference>
	</list>
	<uniqueid name="pbgid" value="133491" />
	<instance_reference name="parent_pbg" value="sbps\races\core\unit_villager_1" />
</instance>